nvidia/dali/plugin/jax/integration.py
nvidia/dali/plugin/numba/fn/experimental/__init__.pyi
nvidia/dali/_autograph/pyct/qual_names.py
nvidia/dali/_autograph/core/converter.py
nvidia/dali/plugin/base_iterator.py
nvidia/dali/plugin/jax/fn/_function_transform.py
nvidia/dali/plugin/numba/fn/__init__.py
nvidia/dali/plugin/jax/fn/_jax_function_impl.py
nvidia/dali/plugin/numba/experimental/__init__.pyi
nvidia/dali/include/dali/operators/random/beta_distribution.h
nvidia/dali/include/dali/operators/math/expressions/expression_impl_gpu_ternary.cuh
nvidia/dali/include/dali/kernels/reduce/reduce_gpu.h
nvidia/dali/experimental/dynamic/__init__.py
nvidia/dali/experimental/dynamic/io/file/__init__.pyi
nvidia/dali/ops/experimental/readers/__init__.pyi
nvidia/dali/include/dali/core/mm/pool_resource_base.h
nvidia/dali/include/dali/operators/sequence/optical_flow/optical_flow_impl/optical_flow_buffer.h
nvidia/dali/plugin/jax/fn/__init__.py
nvidia/dali/plugin/pytorch/__init__.py
nvidia/dali/include/dali/operators/random/noise/gaussian_noise.h
nvidia/dali/include/dali/core/per_stream_pool.h
nvidia/dali/include/dali/operators/decoder/image/jpeg2k.h
nvidia/dali/include/dali/operators/video/decoder/video_decoder_base.h
nvidia/dali/include/dali/pipeline/executor/executor2/stream_assignment.h
nvidia/dali/_autograph/pyct/static_analysis/reaching_fndefs.py
nvidia/dali/_autograph/pyct/origin_info.py
nvidia/dali/include/boost/preprocessor/array/data.hpp
nvidia/dali/include/dali/pipeline/data/dltensor.h
nvidia/dali/include/boost/preprocessor/tuple/elem.hpp
nvidia/dali/include/boost/preprocessor/selection/max.hpp
nvidia/dali/include/boost/preprocessor/slot/slot.hpp
nvidia/dali/include/boost/preprocessor/tuple/detail/is_single_return.hpp
nvidia/dali/include/boost/preprocessor/variadic/detail/has_opt.hpp
nvidia/dali/include/dali/util/s3_filesystem.h
nvidia/dali/_utils/autoserialize.py
nvidia/dali/include/dali/kernels/signal/resampling.h
nvidia/dali/include/boost/preprocessor/list/fold_left.hpp
nvidia_dali_cuda130-1.53.0.dist-info/top_level.txt
nvidia_dali_cuda130-1.53.0.dist-info/entry_points.txt
nvidia_dali_cuda130-1.53.0.dist-info/METADATA
nvidia_dali_cuda130-1.53.0.dist-info/WHEEL
nvidia_dali_cuda130-1.53.0.dist-info/RECORD
