Metadata-Version: 2.4
Name: nvidia-dali-cuda130
Version: 1.53.0
Summary: NVIDIA DALI  for CUDA 13.0. Git SHA: 55113c6cd54624aeebd7e3c0d93b4c4a68a34034
Home-page: https://github.com/NVIDIA/dali
Author: NVIDIA Corporation
License: Apache License 2.0
Classifier: Programming Language :: Python :: 3.9
Classifier: Programming Language :: Python :: 3.10
Classifier: Programming Language :: Python :: 3.11
Classifier: Programming Language :: Python :: 3.12
Classifier: Programming Language :: Python :: 3.13
Requires-Python: >=3.9, <3.14
Requires-Dist: astunparse<=1.6.3,>=1.6.0
Requires-Dist: gast<=0.6.0,>=0.3.3
Requires-Dist: six<=1.17,>=1.16
Requires-Dist: dm-tree<=0.1.8; python_version < "3.10"
Requires-Dist: dm-tree<=0.1.9; python_version >= "3.10"
Requires-Dist: packaging<=25.0
Requires-Dist: nvtx
Requires-Dist: makefun
Requires-Dist: nvidia-nvimgcodec-cu13[all]<0.8.0,>=0.7.0
Requires-Dist: nvidia-libnvcomp-cu13==5.1.0.21
Dynamic: author
Dynamic: classifier
Dynamic: description
Dynamic: description-content-type
Dynamic: home-page
Dynamic: license
Dynamic: requires-dist
Dynamic: requires-python
Dynamic: summary
